fleen/__init__.py
fleen/version.py
fleen-0.0.0.dist-info/METADATA
fleen-0.0.0.dist-info/WHEEL
fleen-0.0.0.dist-info/top_level.txt
fleen-0.0.0.dist-info/RECORD
