Metadata-Version: 2.1
Name: fleen
Version: 0.0.0
Summary: Modular rigging system for Maya
Home-page: https://github.com/lixaft/fleen
Author: Fabien Taxil
Author-email: fabien.taxil@gmail.com
License: MIT
Platform: UNKNOWN
Classifier: Programming Language :: Python :: 3
Classifier: Programming Language :: Python :: 2
Classifier: License :: OSI Approved :: MIT License
Classifier: Operating System :: OS Independent
